binaryai/__init__.py
binaryai/binaryai_file.py
binaryai/client.py
binaryai/client_stub/__init__.py
binaryai/client_stub/ascii_string.py
binaryai/client_stub/base_client.py
binaryai/client_stub/base_model.py
binaryai/client_stub/check_or_upload.py
binaryai/client_stub/check_state.py
binaryai/client_stub/client.py
binaryai/client_stub/compressed_file.py
binaryai/client_stub/create_file.py
binaryai/client_stub/cve_name.py
binaryai/client_stub/download_link.py
binaryai/client_stub/enums.py
binaryai/client_stub/exceptions.py
binaryai/client_stub/file_k_hash.py
binaryai/client_stub/file_malware_probability.py
binaryai/client_stub/file_size.py
binaryai/client_stub/filename.py
binaryai/client_stub/function_info.py
binaryai/client_stub/function_list.py
binaryai/client_stub/function_match.py
binaryai/client_stub/functions_info.py
binaryai/client_stub/input_types.py
binaryai/client_stub/license.py
binaryai/client_stub/license_short_name.py
binaryai/client_stub/mime_type.py
binaryai/client_stub/overview.py
binaryai/client_stub/reanalyze.py
binaryai/client_stub/sca.py
binaryai/client_stub/sha_256.py
binaryai/component.py
binaryai/compressed_file.py
binaryai/cve.py
binaryai/exceptions.py
binaryai/function.py
binaryai/license.py
binaryai/query.graphql
binaryai/upload.py
binaryai/utils.py
binaryai-0.8.4.dist-info/LICENSE
binaryai-0.8.4.dist-info/METADATA
binaryai-0.8.4.dist-info/WHEEL
binaryai-0.8.4.dist-info/RECORD
