Metadata-Version: 2.1
Name: binaryai
Version: 0.8.4
Summary: BinaryAI-SDK is a library provides an abstracted client module to simplify the procedure of uploading file for analysis.
Home-page: https://www.binaryai.cn/
License: GPLv3
Author: binaryai
Author-email: binaryai@tencent.com
Requires-Python: >=3.9,<4.0
Classifier: License :: Other/Proprietary License
Classifier: Programming Language :: Python :: 3
Classifier: Programming Language :: Python :: 3.9
Classifier: Programming Language :: Python :: 3.10
Classifier: Programming Language :: Python :: 3.11
Requires-Dist: deprecated (>=1.2.14,<2.0.0)
Requires-Dist: httpx (>=0.25.0,<0.26.0)
Requires-Dist: pydantic (>=2.3.0,<3.0.0)
Project-URL: Documentation, https://www.binaryai.cn/doc/
Project-URL: Repository, https://github.com/binaryai/sdk/
